{
    "_task_name": {
        "wmt16_translate/cs-en:1.0.0": 114629,
        "wmt14_translate/fr-en:1.0.0": 114189,
        "wmt16_translate/de-en:1.0.0": 52348,
        "wmt16_translate/ru-en:1.0.0": 28591,
        "wmt16_translate/fi-en:1.0.0": 23664,
        "gigaword:1.2.0": 23467,
        "math_dataset/algebra__linear_1d:1.0.0": 22826,
        "sentiment140:1.0.0": 18116,
        "newsroom:1.0.0": 11429,
        "glue/mnli:2.0.0": 8973,
        "wmt16_translate/ro-en:1.0.0": 6876,
        "yelp_polarity_reviews:0.2.0": 6494,
        "snli:1.1.0": 6122,
        "glue/qqp:2.0.0": 4224,
        "cnn_dailymail:3.4.0": 3272,
        "wmt16_translate/tr-en:1.0.0": 2402,
        "huggingface:xsum": 2287,
        "squad/v2.0:3.0.0": 1551,
        "ag_news_subset:1.0.0": 1394,
        "glue/qnli:2.0.0": 1216,
        "gem/wiki_lingua_english_en:1.1.0": 1179,
        "anli/r3:0.1.0": 1132,
        "super_glue/record:1.0.2": 1124,
        "squad/v1.1:3.0.0": 1065,
        "trivia_qa/rc:1.1.0": 1014,
        "natural_questions_open:1.0.0": 999,
        "quac:1.0.0": 951,
        "drop:2.0.0": 878,
        "glue/sst2:2.0.0": 807,
        "gem/common_gen:1.1.0": 779,
        "gem/dart:1.1.0": 681,
        "paws_wiki:1.1.0": 579,
        "multi_news:1.0.0": 505,
        "anli/r2:0.1.0": 501,
        "winogrande:1.1.0": 464,
        "hellaswag:1.1.0": 421,
        "gem/web_nlg_en:1.1.0": 412,
        "para_crawl_enes": 381,
        "gem/e2e_nlg:1.1.0": 375,
        "true_case": 328,
        "word_segment": 326,
        "fix_punct": 324,
        "super_glue/multirc:1.0.2": 319,
        "cosmos_qa:1.0.0": 303,
        "imdb_reviews/plain_text:1.0.0": 269,
        "anli/r1:0.1.0": 198,
        "piqa:1.0.0": 195,
        "samsum:1.0.0": 167,
        "aeslc:1.0.0": 161,
        "bool_q:1.0.0": 107,
        "glue/cola:2.0.0": 98,
        "trec:1.0.0": 74,
        "coqa:1.0.0": 72,
        "glue/stsb:2.0.0": 67,
        "openbookqa:0.1.0": 59,
        "super_glue/wic:1.0.2": 55,
        "lambada:1.0.0": 53,
        "glue/mrpc:2.0.0": 48,
        "opinion_abstracts_rotten_tomatoes": 31,
        "super_glue/rte:1.0.2": 27,
        "ai2_arc/ARC-Easy:1.0.0": 24,
        "opinion_abstracts_idebate": 23,
        "story_cloze/2016:1.0.0": 20,
        "definite_pronoun_resolution:1.1.0": 18,
        "ai2_arc/ARC-Challenge:1.0.0": 16,
        "glue/wnli:2.0.0": 10,
        "unified_qa_science_inst": 6,
        "super_glue/wsc.fixed:1.0.2": 6,
        "super_glue/cb:1.0.2": 4,
        "super_glue/copa:1.0.2": 3
    },
    "_template_type": {
        "zs_opt": 471728
    },
    "_task_source": {
        "Flan2021": 471728
    },
    "_template_idx": {
        "9": 47259,
        "8": 47254,
        "6": 47205,
        "4": 47192,
        "7": 47159,
        "2": 47157,
        "3": 47155,
        "5": 47154,
        "0": 47106,
        "1": 47087
    }
}